README.md
pyproject.toml
setup.cfg
setup.py
src/rptl.egg-info/PKG-INFO
src/rptl.egg-info/SOURCES.txt
src/rptl.egg-info/dependency_links.txt
src/rptl.egg-info/entry_points.txt
src/rptl.egg-info/not-zip-safe
src/rptl.egg-info/requires.txt
src/rptl.egg-info/top_level.txt
src/timelapse/__main__.py
src/timelapse/camera.py
src/timelapse/daemon.py
src/timelapse/oldmain.py
src/timelapse/sort_colour_profile.py
src/timelapse/timestamp_images.py
src/timelapse/video.py