Metadata-Version: 2.1
Name: rptl
Version: 0.0.1
Summary: This tool is designed to take still images every 5 minutes using a raspberry pi camera. Then turn them images into a timelapse video.
Requires-Dist: pyzmq
